Metadata-Version: 1.0
Name: gabi-distri
Version: 1.0
Summary: Gaussian and Binomial distributions
Home-page: UNKNOWN
Author: Ope Banjo
Author-email: UNKNOWN
License: UNKNOWN
Platform: UNKNOWN
